{
  "hash": "a97a2267",
  "browserHash": "dd18d3ab",
  "optimized": {
    "vue": {
      "src": "../../../../../../node_modules/.pnpm/vue@3.2.47/node_modules/vue/dist/vue.runtime.esm-bundler.js",
      "file": "vue.js",
      "fileHash": "c00f4205",
      "needsInterop": false
    },
    "vitepress-plugin-google-analytics": {
      "src": "../../../../../../node_modules/.pnpm/vitepress-plugin-google-analytics@1.0.2/node_modules/vitepress-plugin-google-analytics/dist/index.mjs",
      "file": "vitepress-plugin-google-analytics.js",
      "fileHash": "e4e1d2fb",
      "needsInterop": false
    },
    "chart.js/auto/auto.mjs": {
      "src": "../../../../../../node_modules/.pnpm/chart.js@3.9.1/node_modules/chart.js/auto/auto.mjs",
      "file": "chart__js_auto_auto__mjs.js",
      "fileHash": "85c5998b",
      "needsInterop": false
    },
    "dropzone": {
      "src": "../../../../../../node_modules/.pnpm/dropzone@6.0.0-beta.2/node_modules/dropzone/dist/dropzone.mjs",
      "file": "dropzone.js",
      "fileHash": "ad531afb",
      "needsInterop": false
    },
    "dayjs": {
      "src": "../../../../../../node_modules/.pnpm/dayjs@1.11.7/node_modules/dayjs/dayjs.min.js",
      "file": "dayjs.js",
      "fileHash": "9c3d562a",
      "needsInterop": true
    },
    "dayjs/plugin/customParseFormat": {
      "src": "../../../../../../node_modules/.pnpm/dayjs@1.11.7/node_modules/dayjs/plugin/customParseFormat.js",
      "file": "dayjs_plugin_customParseFormat.js",
      "fileHash": "c4c523ad",
      "needsInterop": true
    },
    "dayjs/plugin/isBetween": {
      "src": "../../../../../../node_modules/.pnpm/dayjs@1.11.7/node_modules/dayjs/plugin/isBetween.js",
      "file": "dayjs_plugin_isBetween.js",
      "fileHash": "1458f00a",
      "needsInterop": true
    },
    "libphonenumber-js": {
      "src": "../../../../../../node_modules/.pnpm/libphonenumber-js@1.10.21/node_modules/libphonenumber-js/index.js",
      "file": "libphonenumber-js.js",
      "fileHash": "878d325a",
      "needsInterop": false
    },
    "libphonenumber-js/examples.mobile.json": {
      "src": "../../../../../../node_modules/.pnpm/libphonenumber-js@1.10.21/node_modules/libphonenumber-js/examples.mobile.json.js",
      "file": "libphonenumber-js_examples__mobile__json.js",
      "fileHash": "3779def9",
      "needsInterop": false
    },
    "dayjs/plugin/weekday": {
      "src": "../../../../../../node_modules/.pnpm/dayjs@1.11.7/node_modules/dayjs/plugin/weekday.js",
      "file": "dayjs_plugin_weekday.js",
      "fileHash": "0bf8ec52",
      "needsInterop": true
    }
  },
  "chunks": {
    "chunk-RSJERJUL": {
      "file": "chunk-RSJERJUL.js"
    }
  }
}